[
  {
    "course": {
      "name": "Large Deviations",
      "code": "MA 396",
      "instructor": "Anirban Basak"
    },
    "timings": [
      {
        "choice": 1,
        "timing": {
          "days": "Tue, Thu",
          "times": "2:00 - 3:30"
        }
      },
      {
        "choice": 2,
        "timing": {
          "days": "Tue, Thu",
          "times": "11:30 - 1:00"
        }
      },
      {
        "choice": 3,
        "timing": {
          "days": "Mon, Wed, Fri",
          "times": "2:00 - 3:00"
        }
      },
      {
        "choice": 4,
        "timing": {
          "days": "Tue, Thu",
          "times": "3:30 - 5: 00"
        }
      }
    ]
  },
  {
    "course": {
      "name": "Introduction to Algebraic Topology",
      "code": "MA 232",
      "instructor": "Siddhartha Gadgil"
    },
    "timings": [
      {
        "choice": 1,
        "timing": {
          "days": "Tue, Thu",
          "times": "8:30 - 10:00"
        }
      },
      {
        "choice": 2,
        "timing": {
          "days": "Mon, Wed, Fri",
          "times": "9:00 - 10:00"
        }
      },
      {
        "choice": 3,
        "timing": {
          "days": "Mon, Wed, Fri",
          "times": "10:00 - 11:00"
        }
      },
      {
        "choice": 3,
        "timing": {
          "days": "Tue, Thu",
          "times": "10:00 - 11:30"
        }
      }
    ]
  },
  {
    "course": {
      "name": "Representation Theory of Finite Groups",
      "code": "MA 220",
      "instructor": "Pooja Singla"
    },
    "timings": [
      {
        "choice": 1,
        "timing": {
          "days": "Tue, Thu",
          "times": "11:30 - 1:00"
        }
      },
      {
        "choice": 2,
        "timing": {
          "days": "Mon, Wed, Fri",
          "times": "12:00 - 1:00"
        }
      },
      {
        "choice": 3,
        "timing": {
          "days": "Tue, Thu",
          "times": "10:00 - 11:30"
        }
      },
      {
        "choice": 4,
        "timing": {
          "days": "Mon, Wed, Fri",
          "times": "11:00 - 12:00"
        }
      }
    ]
  },
  {
    "course": {
      "name": "Linear Algebra",
      "code": "MA 219",
      "instructor": "Vamsi Pingali"
    },
    "timings": [
      {
        "choice": 1,
        "timing": {
          "days": "Tue, Thu",
          "times": "2:00 - 3:30"
        }
      },
      {
        "choice": 2,
        "timing": {
          "days": "Tue, Thu",
          "times": "10:00 - 11:30"
        }
      },
      {
        "choice": 3,
        "timing": {
          "days": "Mon, Wed, Fri",
          "times": "2:00 - 3:00"
        }
      },
      {
        "choice": 4,
        "timing": {
          "days": "Tue, Thu",
          "times": "3:30 - 5: 00"
        }
      }
    ]
  },
  {
    "course": {
      "name": "Riemannian Geometry",
      "code": "MA 333",
      "instructor": "Ved Datar"
    },
    "timings": [
      {
        "choice": 1,
        "timing": {
          "days": "Tue, Thu",
          "times": "2:00 - 3:30"
        }
      },
      {
        "choice": 1,
        "timing": {
          "days": "Tue, Thu",
          "times": "10:00 - 11:30"
        }
      },
      {
        "choice": 2,
        "timing": {
          "days": "Tue, Thu",
          "times": "3:30 - 5: 00"
        }
      },
      {
        "choice": 3,
        "timing": {
          "days": "Mon, Wed, Fri",
          "times": "10:00 - 11:00"
        }
      },
      {
        "choice": 4,
        "timing": {
          "days": "Mon, Wed, Fri",
          "times": "11:00 - 12:00"
        }
      }
    ]
  },
  {
    "course": {
      "name": "Algebra I",
      "code": "MA 212",
      "instructor": "Apoorva Khare"
    },
    "timings": [
      {
        "choice": 1,
        "timing": {
          "days": "Tue, Thu",
          "times": "2:00 - 3:30"
        }
      },
      {
        "choice": 1,
        "timing": {
          "days": "Tue, Thu",
          "times": "11:30 - 1:00"
        }
      },
      {
        "choice": 2,
        "timing": {
          "days": "Tue, Thu",
          "times": "3:30 - 5: 00"
        }
      },
      {
        "choice": 2,
        "timing": {
          "days": "Tue, Thu",
          "times": "10:00 - 11:30"
        }
      },
      {
        "choice": 3,
        "timing": {
          "days": "Mon, Wed, Fri",
          "times": "2:00 - 3:00"
        }
      }
    ]
  },
  {
    "course": {
      "name": "Probability Theory",
      "code": "MA 361",
      "instructor": "Manjunath Krishnapur"
    },
    "timings": [
      {
        "choice": 1,
        "timing": {
          "days": "Tue, Thu",
          "times": "3:30 - 5: 00"
        }
      },
      {
        "choice": 2,
        "timing": {
          "days": "Mon, Wed, Fri",
          "times": "11:00 - 12:00"
        }
      },
      {
        "choice": 3,
        "timing": {
          "days": "Tue, Thu",
          "times": "2:00 - 3:30"
        }
      }
    ]
  },
  {
    "course": {
      "name": "Matrix Analysis & positivity",
      "code": "MA 341",
      "instructor": "Apoorva Khare"
    },
    "timings": [
      {
        "choice": 1,
        "timing": {
          "days": "Tue, Thu",
          "times": "2:00 - 3:30"
        }
      },
      {
        "choice": 1,
        "timing": {
          "days": "Tue, Thu",
          "times": "3:30 - 5: 00"
        }
      },
      {
        "choice": 2,
        "timing": {
          "days": "Tue, Thu",
          "times": "11:30 - 1:00"
        }
      },
      {
        "choice": 2,
        "timing": {
          "days": "Tue, Thu",
          "times": "10:00 - 11:30"
        }
      },
      {
        "choice": 3,
        "timing": {
          "days": "Mon, Wed, Fri",
          "times": "2:00 - 3:00"
        }
      }
    ]
  },
  {
    "course": {
      "name": "Probability Models",
      "code": "MA 261",
      "instructor": "Arvind Ayyer"
    },
    "timings": [
      {
        "choice": 1,
        "timing": {
          "days": "Mon, Wed, Fri",
          "times": "10:00 - 11:00"
        }
      },
      {
        "choice": 2,
        "timing": {
          "days": "Mon, Wed, Fri",
          "times": "11:00 - 12:00"
        }
      },
      {
        "choice": 3,
        "timing": {
          "days": "Mon, Wed, Fri",
          "times": "3:00 - 4:00"
        }
      },
      {
        "choice": 4,
        "timing": {
          "days": "Mon, Wed, Fri",
          "times": "2:00 - 3:00"
        }
      }
    ]
  },
  {
    "course": {
      "name": "Introduction to Graph Theory",
      "code": "MA 216",
      "instructor": "Arvind Ayyer"
    },
    "timings": [
      {
        "choice": 1,
        "timing": {
          "days": "Tue, Thu",
          "times": "10:00 - 11:30"
        }
      },
      {
        "choice": 2,
        "timing": {
          "days": "Tue, Thu",
          "times": "2:00 - 3:30"
        }
      },
      {
        "choice": 3,
        "timing": {
          "days": "Mon, Wed, Fri",
          "times": "3:00 - 4:00"
        }
      },
      {
        "choice": 4,
        "timing": {
          "days": "Tue, Thu",
          "times": "3:30 - 5: 00"
        }
      }
    ]
  },
  {
    "course": {
      "name": "Functional Analysis",
      "code": "MA 223",
      "instructor": "S. Thangavelu"
    },
    "timings": [
      {
        "choice": 1,
        "timing": {
          "days": "Mon, Wed, Fri",
          "times": "10:00 - 11:00"
        }
      },
      {
        "choice": 2,
        "timing": {
          "days": "Mon, Wed, Fri",
          "times": "11:00 - 12:00"
        }
      },
      {
        "choice": 3,
        "timing": {
          "days": "Mon, Wed, Fri",
          "times": "12:00 - 1:00"
        }
      }
    ]
  },
  {
    "course": {
      "name": "Topics in Morse Theory",
      "code": "MA 306",
      "instructor": "Arun Maiti"
    },
    "timings": [
      {
        "choice": 1,
        "timing": {
          "days": "Mon, Wed, Fri",
          "times": "2:00 - 3:00"
        }
      },
      {
        "choice": 2,
        "timing": {
          "days": "Mon, Wed, Fri",
          "times": "11:00 - 12:00"
        }
      },
      {
        "choice": 3,
        "timing": {
          "days": "Mon, Wed, Fri",
          "times": "3:00 - 4:00"
        }
      }
    ]
  }
]